Metadata-Version: 2.1
Name: python-gc-benchmark
Version: 0.1.1
Summary: Python GC benchmark suite
Home-page: UNKNOWN
Author: Joannah Nanjekye
Author-email: jnanjeky@unb.ca
License: MIT license
Platform: UNKNOWN
Classifier: Intended Audience :: Developers
